pk3/README.md
pk3/__init__.py
pk3/__main__.py
pk3/publish.py
pk3/readme.py
pk3/tag.py
pk3/version.py
pk3-0.1.4.dist-info/METADATA
pk3-0.1.4.dist-info/WHEEL
pk3-0.1.4.dist-info/entry_points.txt
pk3-0.1.4.dist-info/top_level.txt
pk3-0.1.4.dist-info/RECORD
